tr/__init__.py
turkcepy/__init__.py
turkcepy/cevirici.py
turkcepy/donguler.py
turkcepy/dosya.py
turkcepy/matematik.py
turkcepy/temel.py
turkcepy/veri_yapilari.py
turkcepy-1.0.3.dist-info/METADATA
turkcepy-1.0.3.dist-info/WHEEL
turkcepy-1.0.3.dist-info/top_level.txt
turkcepy-1.0.3.dist-info/RECORD
