Metadata-Version: 2.4
Name: turkcepy
Version: 1.0.3
Summary: Türkçe anahtar kelimelerle Python programlama
Home-page: https://pypi.org/project/turkcepy/
Author: Yılmaz Kutsal
Author-email: Yılmaz Kutsal <ykutsal@gmail.com>
License-Expression: MIT
Keywords: python,turkce,egitim,keywords,turkish
Classifier: Programming Language :: Python :: 3
Classifier: Programming Language :: Python :: 3.8
Classifier: Programming Language :: Python :: 3.9
Classifier: Programming Language :: Python :: 3.10
Classifier: Programming Language :: Python :: 3.11
Classifier: Programming Language :: Python :: 3.12
Classifier: Intended Audience :: Education
Classifier: Topic :: Education
Requires-Python: >=3.8
